LICENSE
MANIFEST.in
README.md
setup.py
_cffi_build/__init__.py
_cffi_build/pyshaderc_build.py
_cffi_build/shaderc-cb4f0f6.zip
_cffi_build/shaderc.h
_cffi_build/shaderc_build.py
pyshaderc/__init__.py
pyshaderc.egg-info/PKG-INFO
pyshaderc.egg-info/SOURCES.txt
pyshaderc.egg-info/dependency_links.txt
pyshaderc.egg-info/requires.txt
pyshaderc.egg-info/top_level.txt