Metadata-Version: 2.1
Name: pyshaderc
Version: 1.1.3
Summary: Python CFFI binding for shaderc
Home-page: http://github.com/realitix/pyshaderc
Author: realitix
Author-email: realitix@gmail.com
License: Apache 2.0
Platform: UNKNOWN
Classifier: Development Status :: 4 - Beta
Classifier: Intended Audience :: Developers
Classifier: License :: OSI Approved :: Apache Software License
Classifier: Natural Language :: English
Classifier: Programming Language :: Python :: 3.5
Classifier: Programming Language :: Python :: Implementation :: CPython
License-File: LICENSE
